make_pdf/__init__.py
make_pdf/__main__.py
make_pdf/base.py
make_pdf/constants.py
make_pdf/enums.py
make_pdf/utils.py
make_pdf/commands/__init__.py
make_pdf/commands/letter.py
make_pdf/commands/newsletter.py
make_pdf/commands/param_extractor.py
make_pdf/commands/plain.py
make_pdf/commands/presentation.py
make_pdf/converters/__init__.py
make_pdf/converters/base_arg_generator.py
make_pdf/converters/file_converter.py
make_pdf/converters/letter_arg_generator.py
make_pdf/converters/plain_and_newsletter_arg_generator.py
make_pdf/converters/presentation_arg_generator.py
make_pdf/preprocessors/__init__.py
make_pdf/preprocessors/criticmarkup_preprocessor.py
make_pdf/preprocessors/diff_preprocessor.py
make_pdf/preprocessors/file_stitcher.py
make_pdf/resources/filters/criticmarkup.lua
make_pdf/resources/filters/currentdate.lua
make_pdf/resources/filters/fences.lua
make_pdf/resources/filters/include-files.lua
make_pdf/resources/locales/base.pot
make_pdf/resources/locales/de/LC_MESSAGES/base.mo
make_pdf/resources/locales/de/LC_MESSAGES/base.po
make_pdf/resources/locales/en/LC_MESSAGES/base.mo
make_pdf/resources/locales/en/LC_MESSAGES/base.po
make_pdf/resources/tex/default-header.tex
make_pdf/resources/tex/final-hook.tex
make_pdf/resources/tex/localization.tex
make_pdf/resources/tex/main.tex
make_pdf/resources/tex/packages.tex
make_pdf/resources/tex/utils.tex
make_pdf/resources/tex/letter/after-letter.tex
make_pdf/resources/tex/letter/before-letter.tex
make_pdf/resources/tex/letter/lettervars-template.tex
make_pdf/resources/tex/plain_and_newsletter/newsletter.tex
make_pdf/resources/tex/plain_and_newsletter/plain.tex
make_pdf/resources/tex/presentation/presentation.tex
make_pdf-0.1.0.post4.dist-info/entry_points.txt
make_pdf-0.1.0.post4.dist-info/LICENSE
make_pdf-0.1.0.post4.dist-info/WHEEL
make_pdf-0.1.0.post4.dist-info/METADATA
make_pdf-0.1.0.post4.dist-info/RECORD
