Metadata-Version: 2.1
Name: make_pdf
Version: 0.1.0.post4
Summary: A command line tool to convert files to fancy PDFs
Keywords: cli
Author-email: EorlBruder <eorl@bruder.space>
Requires-Python: >=3.6,<4
Classifier: Environment :: Console
Classifier: Development Status :: 2 - Pre-Alpha
Classifier: Intended Audience :: End Users/Desktop
Classifier: License :: OSI Approved :: GNU Affero General Public License v3 or later (AGPLv3+)
Classifier: Natural Language :: English
Classifier: Operating System :: MacOS :: MacOS X
Classifier: Operating System :: POSIX
Classifier: Operating System :: POSIX :: BSD
Classifier: Operating System :: POSIX :: Linux
Classifier: Operating System :: Microsoft :: Windows
Classifier: Programming Language :: Python
Classifier: Programming Language :: Python :: 3
Classifier: Programming Language :: Python :: 3 :: Only
Classifier: Programming Language :: Python :: 3.6
Classifier: Programming Language :: Python :: 3.7
Classifier: Programming Language :: Python :: 3.8
Classifier: Programming Language :: Python :: 3.9
Classifier: Topic :: Text Processing
Requires-Dist: pypandoc >=1.6,<2
Requires-Dist: click >=8,<9
Requires-Dist: appdirs >=1.4,<2
Requires-Dist: towncrier >=21.3,<22 ; extra == "changelog"
Requires-Dist: black[d] >=21.4b0,<22 ; extra == "dev"
Requires-Dist: babel >=2.7,<3 ; extra == "dev"
Requires-Dist: sphinx >=4.1,<5 ; extra == "doc"
Requires-Dist: sphinx-intl >=2,<3 ; extra == "doc"
Requires-Dist: flit >=3.3,<4 ; extra == "publish"
Requires-Dist: pytest >=6.2.4,<7 ; extra == "test"
Requires-Dist: pytest-mock >=3.6,<4 ; extra == "test"
Project-URL: Documentation, https://make-pdf.de/
Project-URL: Homepage, https://make-pdf.de/
Project-URL: Source, https://git.eorlbruder.de/EorlBruder/make_pdf
Provides-Extra: changelog
Provides-Extra: dev
Provides-Extra: doc
Provides-Extra: publish
Provides-Extra: test
